githubV3py/__init__.py
githubV3py/actions.py
githubV3py/activity.py
githubV3py/apps.py
githubV3py/checks.py
githubV3py/code_scanning.py
githubV3py/codes_of_conduct.py
githubV3py/emojis.py
githubV3py/enterprise_admin.py
githubV3py/gists.py
githubV3py/git.py
githubV3py/githubclient.py
githubV3py/githubclientbase.py
githubV3py/githubclientclasses.py
githubV3py/githubclientexceptions.py
githubV3py/gitignore.py
githubV3py/issues.py
githubV3py/licenses.py
githubV3py/markdown.py
githubV3py/meta.py
githubV3py/oauth_authorizations.py
githubV3py/orgs.py
githubV3py/projects.py
githubV3py/pulls.py
githubV3py/rate_limit.py
githubV3py/reactions.py
githubV3py/repos.py
githubV3py/search.py
githubV3py/secret_scanning.py
githubV3py/teams.py
githubV3py/users.py
githubV3py-1.0.1.dist-info/LICENSE
githubV3py-1.0.1.dist-info/METADATA
githubV3py-1.0.1.dist-info/WHEEL
githubV3py-1.0.1.dist-info/top_level.txt
githubV3py-1.0.1.dist-info/RECORD
