Metadata-Version: 2.1
Name: githubV3py
Version: 1.0.1
Summary: Python API for accessing GitHub
Home-page: https://github.com/AndrewOfC/githubpy
Author: Andrew Page
Author-email: andrew.e.page@gmail.com
License: UNKNOWN
Project-URL: Bug Tracker, https://github.com/AndrewOfC/githubpy/issues
Keywords: [ github,api,REST,git ]
Platform: UNKNOWN
Classifier: Programming Language :: Python :: 3
Classifier: License :: OSI Approved :: MIT License
Classifier: Operating System :: OS Independent
Requires-Python: >=3.6
License-File: LICENSE
Requires-Dist: requests
